{

    "Variedade": "Variedades",

    "C Bebidas": "Conveniencia",

    "Presentes": "Eletronicos",

    "Cama Mesa Banh": "Cama Mesa Banho",

    "Bomboniere": "Conveniencia",

    "Bebidas": "Conveniencia",

    "Alimentos": "Conveniencia",

    "PFesta": "Conveniencia",

    "Limpeza": "Conveniencia",

    "Cozinha": "Utensilios",

    "CFesta": "Conveniencia",

    "Acess Frio": "Bijuterias",

    "Toalha P Metro": "Cama Mesa Banho",

    "Maquiagem": "Bijuterias",

    "Acessorio De Banhei": "Utilidades",

    "Iluminacao": "Led",

    "Perfumaria": "Bijuterias",

    "P Perfumaria": "Bijuterias",

    "Leds": "Led",

    "B Perfumaria": "Bijuterias",

    "Ferramenta": "Led",

    "Porta Retrato": "Decoracao",

    "Bolsas Malas Mochila": "Bijuterias",

    "Quadros": "Decoracao",

    "2.0": "Bijuterias",

    "Lixeira": "Utilidades",

    "Cesto E Balde": "Utilidades",

    "Espelho": "Decoracao",

    "Vestuario": "Bijuterias",

    "Armarinhos": "Papelaria",

    "Infantil": "Brinquedos",

    "Moveis": "Decoracao",

    "Eletro Domestico": "Utilidades",

    "Loja": "Bijuterias",

    "Fantasia Personarge": "Brinquedos",

    "Corte De Toalha": "Cama Mesa Banho",

    "Lazer Camping": "Brinquedos",

    "Filtros": "Led",

    "Bazar": "Decoracao",

    "Calcados": "Bijuterias",

    "Aramados": "Utensilios",

    "Fantasia": "Bijuterias",

    "Cabelo": "Bijuterias",

    "Lustres": "Led",

    "Metro": "Cama Mesa Banho",

    "Brinquedo": "Brinquedos",

    "Papelaria": "Papelaria",

    "Variedades": "Variedades",

    "Bijuterias": "Bijuterias",

    "Conveniencia": "Conveniencia",

    "Cama Mesa Banho": "Cama Mesa Banho",

    "Brinquedos": "Brinquedos",

    "Eletronicos": "Eletronicos",

    "Utilidades": "Utilidades",

    "Utensilios": "Utensilios",

    "Led": "Led",

    "Decoracao": "Decoracao",

    "Flores": "Pet/Flores",

    "Pet": "Pet/Flores",

    "Carnaval": "Carnaval",

    "Natal": "Natal",

    "Kites": "Kites",

    "Produtos para Revenda": "Produtos para Revenda",

    "Estacionamento": "Estacionamento",

    "Junina": "Junina",

    "Kits": "Kits",

    "Diversos": "Diversos",

    "Quiosq": "Quiosq",

    "Materiais e Produtos": "Materiais e Produtos",

    "Desp G Administrativa": "Desp G Administrativa",

    "Despesas Gerais": "Despesas Gerais",

    "Desp G Pessoal": "Desp G Pessoal",

    "Itens da Neg Financeira": "Itens da Neg Financeira",

    "Uso e Consumo": "Uso e Consumo",

    "Desp F Operações": "Desp F Operações",

    "Arte e Desenho": "Papelaria",
    "Brinquedo Sazonais": "Brinquedos",
    "Acessorios Especiais": "Bijuterias",
    "Vidros": "Variedades",
    "Plasticos": "Utilidades",
    "Panelas e Recipientes": "Utensilios",
    "Complementares Textil": "Cama Mesa Banho",
    "Objeto Decorativo": "Decoracao",
    "Embalagens": "Utilidades",
    "Cães e Gatos": "Pet/Flores",
    "Fantasias Sazonais": "Fantasia",
    "Enfeites Natalinos": "Natal",
    "Kites Comemorativos": "Kites",
    "Lampadas": "Led",
    "Materiais para Consumo": "Uso e Consumo"

}